<?xml version="1.0" encoding="UTF-8"?>
<!DOCTYPE mapper PUBLIC "-//mybatis.org//DTD Mapper 3.0//EN" "http://mybatis.org/dtd/mybatis-3-mapper.dtd">
<mapper namespace="com.su.mall.portal.dao.HomeDao">
    <!-- 改为使用 resultType -->
    <select id="getRecommendBrandList" resultType="com.su.mall.model.PmsBrand">
        SELECT b.*
        FROM
            sms_home_brand hb
            LEFT JOIN pms_brand b ON hb.brand_id = b.id
        WHERE
            hb.recommend_status = 1
            AND b.show_status = 1
        ORDER BY
            hb.sort desc
        LIMIT #{offset}, #{limit}
    </select>

    <!-- 获取秒杀商品列表 - 从每日快照表读取库存 -->
    <select id="getFlashProductList" resultType="com.su.mall.portal.domain.FlashPromotionProduct">
        SELECT
            p.*,
            pr.id flash_promotion_relation_id,
            pr.flash_promotion_id,
            pr.flash_promotion_session_id,
            pr.flash_promotion_price,
            ds.stock flash_promotion_count,
            pr.flash_promotion_limit,
            pr.original_count flash_promotion_original_count,
            ds.sold flash_promotion_sold
        FROM
            sms_flash_promotion_product_relation pr
            LEFT JOIN pms_product p ON pr.product_id = p.id
            LEFT JOIN sms_flash_promotion_daily_stock ds ON pr.id = ds.relation_id AND ds.batch_date = CURDATE()
        WHERE
            pr.flash_promotion_id = #{flashPromotionId}
            AND pr.flash_promotion_session_id = #{sessionId}
            AND pr.flash_promotion_price IS NOT NULL
            AND COALESCE(ds.stock, 0) > 0
            AND p.delete_status = 0
            AND p.publish_status = 1
        ORDER BY
            pr.sort ASC
    </select>

    <!-- 改为使用 resultType -->
    <select id="getNewProductList" resultType="com.su.mall.model.PmsProduct">
        SELECT p.*
        FROM
            sms_home_new_product hp
            LEFT JOIN pms_product p ON hp.product_id = p.id
        WHERE
            hp.recommend_status = 1
            AND p.publish_status = 1
        ORDER BY
            hp.sort desc
        LIMIT #{offset}, #{limit};
    </select>

    <!-- 改为使用 resultType -->
    <select id="getHotProductList" resultType="com.su.mall.model.PmsProduct">
        SELECT p.*
        FROM
            sms_home_recommend_product hp
            LEFT JOIN pms_product p ON hp.product_id = p.id
        WHERE
            hp.recommend_status = 1
            AND p.publish_status = 1
        ORDER BY
            hp.sort desc
        LIMIT #{offset}, #{limit};
    </select>

    <!-- 改为使用 resultType -->
    <select id="getRecommendSubjectList" resultType="com.su.mall.model.CmsSubject">
        SELECT s.*
        FROM
            sms_home_recommend_subject hs
            LEFT JOIN cms_subject s ON hs.subject_id = s.id
        WHERE
            hs.recommend_status = 1
            AND s.show_status = 1
        ORDER BY
            hs.sort desc
        LIMIT #{offset}, #{limit};
    </select>
</mapper>
